{
  "indicator": "ADX",
  "group": "Momentum Indicators",
  "params": {
    "timeperiod": 14
  },
  "warmup_bars": 27,
  "checkpoints": [
    {
      "index": 50,
      "date": "2019-03-31",
      "real": 36.89279404472813
    },
    {
      "index": 60,
      "date": "2020-01-31",
      "real": 40.48098892303158
    },
    {
      "index": 70,
      "date": "2020-11-30",
      "real": 39.17961648616019
    },
    {
      "index": 80,
      "date": "2021-09-30",
      "real": 28.792505887568716
    },
    {
      "index": 90,
      "date": "2022-07-31",
      "real": 18.32079704578295
    },
    {
      "index": 100,
      "date": "2023-05-31",
      "real": 21.007554409126875
    },
    {
      "index": 110,
      "date": "2024-03-31",
      "real": 21.633451180793152
    }
  ]
}